{
  "project_info": {
    "project_number": "959630536421",
    "project_id": "stylesphere-9e865",
    "storage_bucket": "stylesphere-9e865.firebasestorage.app"
  },
  "client": [
    {
      "client_info": {
        "mobilesdk_app_id": "1:959630536421:android:7f24a1f27fb4440394ee0c",
        "android_client_info": {
          "package_name": "com.style_sphere"
        }
      },
      "oauth_client": [],
      "api_key": [
        {
          "current_key": "AIzaSyCbsjtgRh4bFfwaw0Rt0afblaG8Z82Fzus"
        }
      ],
      "services": {
        "appinvite_service": {
          "other_platform_oauth_client": []
        }
      }
    }
  ],
  "configuration_version": "1"
}